[
  {
    "title": "ODD RITUAL",
    "slug": "odd-ritual",
    "awwwards_url": "https://www.awwwards.com/sites/odd-ritual",
    "site_url": "",
    "categories": [
      "NEW",
      "New",
      "video"
    ],
    "color_palette": [
      "#c8c8c8",
      "#282828",
      "#505050"
    ],
    "folder": "2026-04-12_odd-ritual",
    "collected_at": "2026-04-12"
  },
  {
    "title": "MERSI",
    "slug": "mersi",
    "awwwards_url": "https://www.awwwards.com/sites/mersi",
    "site_url": "",
    "categories": [
      "NEW",
      "New",
      "video"
    ],
    "color_palette": [
      "#c8c8c8",
      "#282828",
      "#505050"
    ],
    "folder": "2026-04-12_mersi",
    "collected_at": "2026-04-12"
  },
  {
    "title": "ICOMAT",
    "slug": "icomat",
    "awwwards_url": "https://www.awwwards.com/sites/icomat",
    "site_url": "",
    "categories": [
      "NEW",
      "New",
      "Business & Corporate"
    ],
    "color_palette": [
      "#c8c8c8",
      "#282828",
      "#505050"
    ],
    "folder": "2026-04-12_icomat",
    "collected_at": "2026-04-12"
  },
  {
    "title": "NINE TO FIVE",
    "slug": "nine-to-five",
    "awwwards_url": "https://www.awwwards.com/sites/nine-to-five",
    "site_url": "",
    "categories": [
      "NEW",
      "New",
      "video"
    ],
    "color_palette": [
      "#c8c8c8",
      "#285050",
      "#282828"
    ],
    "folder": "2026-04-12_nine-to-five",
    "collected_at": "2026-04-12"
  },
  {
    "title": "MAXIMA THERAPY",
    "slug": "maxima-therapy",
    "awwwards_url": "https://www.awwwards.com/sites/maxima-therapy",
    "site_url": "",
    "categories": [
      "New",
      "New",
      "video"
    ],
    "color_palette": [
      "#c8c8c8",
      "#0050f0",
      "#282828"
    ],
    "folder": "2026-04-12_maxima-therapy",
    "collected_at": "2026-04-12"
  },
  {
    "title": "CHAMPIONS FOR GOOD",
    "slug": "champions-for-good",
    "awwwards_url": "https://www.awwwards.com/sites/champions-for-good",
    "site_url": "",
    "categories": [
      "New",
      "New",
      "video"
    ],
    "color_palette": [
      "#c8c8c8",
      "#c878f0",
      "#282828"
    ],
    "folder": "2026-04-12_champions-for-good",
    "collected_at": "2026-04-12"
  },
  {
    "title": "ARTEM SHCHERBAN PORTFOLIO",
    "slug": "artem-shcherban-portfolio",
    "awwwards_url": "https://www.awwwards.com/sites/artem-shcherban-portfolio",
    "site_url": "",
    "categories": [
      "New",
      "New",
      "2"
    ],
    "color_palette": [
      "#c8c8c8",
      "#282828",
      "#a0a0a0"
    ],
    "folder": "2026-04-12_artem-shcherban-portfolio",
    "collected_at": "2026-04-12"
  },
  {
    "title": "SSSCRIPT™ APP",
    "slug": "ssscripttm-app",
    "awwwards_url": "https://www.awwwards.com/sites/ssscripttm-app",
    "site_url": "",
    "categories": [
      "New",
      "New",
      "Mobile & Apps"
    ],
    "color_palette": [
      "#c8c8c8",
      "#282828",
      "#f0f078"
    ],
    "folder": "2026-04-12_ssscripttm-app",
    "collected_at": "2026-04-12"
  }
]